bsbr/__init__.py
bsbr/bsbr.py
bsbr/example.py
bsbr/py.typed
bsbr/utils/__init__.py
bsbr-0.1.1.dist-info/METADATA
bsbr-0.1.1.dist-info/WHEEL
bsbr-0.1.1.dist-info/licenses/LICENSE
bsbr-0.1.1.dist-info/RECORD
