Metadata-Version: 2.4
Name: bsbr
Version: 0.1.1
Summary: Block Sparse Attention with Block Retrieval
Author-email: jacob <jacobfv123@gmail.com>
License-File: LICENSE
Requires-Python: >=3.12
Requires-Dist: matplotlib>=3.10.1
Requires-Dist: numpy>=2.2.4
Requires-Dist: pandas>=2.2.3
Requires-Dist: pytest>=8.3.5
Requires-Dist: seaborn>=0.13.2
Requires-Dist: torch>=2.6.0
Provides-Extra: extras
Requires-Dist: matplotlib>=3.10.1; extra == 'extras'
Requires-Dist: numpy>=2.2.4; extra == 'extras'
Requires-Dist: pandas>=2.2.3; extra == 'extras'
Requires-Dist: pytest>=8.3.5; extra == 'extras'
Requires-Dist: seaborn>=0.13.2; extra == 'extras'
Requires-Dist: torch>=2.6.0; extra == 'extras'
